kalyke/__init__.py
kalyke/kalyke.py
kalyke/seaborn/__init__.py
kalyke/seaborn/styles.py
kalyke-0.2.0.dist-info/METADATA
kalyke-0.2.0.dist-info/RECORD
kalyke-0.2.0.dist-info/WHEEL
kalyke-0.2.0.dist-info/top_level.txt
