Metadata-Version: 2.1
Name: kalyke
Version: 0.2.0
Summary: A mixed-bag of graphing utilities for use in Jupyter notebook projects.
Home-page: https://github.com/barrysmyth/kalyke
Author: Barry Smyth
Author-email: barry.smyth@ucd.ie
License: MIT license
Keywords: kalyke
Platform: UNKNOWN
Classifier: Development Status :: 2 - Pre-Alpha
Classifier: Intended Audience :: Developers
Classifier: License :: OSI Approved :: MIT License
Classifier: Natural Language :: English
Classifier: Programming Language :: Python :: 2
Classifier: Programming Language :: Python :: 2.7
Classifier: Programming Language :: Python :: 3
Classifier: Programming Language :: Python :: 3.4
Classifier: Programming Language :: Python :: 3.5
Classifier: Programming Language :: Python :: 3.6
Classifier: Programming Language :: Python :: 3.7
